{
  "repository": "moznion/cccc/complexity",
  "ref": "refs/heads/main",
  "commit": "a68f8ca34145af2aa11fde37d58fcb91baf0961f",
  "timestamp": "2026-07-11T04:35:46.572316919Z",
  "custom_metrics": [
    {
      "key": "code_complexity",
      "name": "Code Complexity (src)",
      "metrics": [
        {
          "key": "function_count",
          "name": "Function count",
          "value": 1342
        },
        {
          "key": "cognitive_sum",
          "name": "Cognitive: total",
          "value": 1129
        },
        {
          "key": "cognitive_max",
          "name": "Cognitive: max",
          "value": 42
        },
        {
          "key": "cognitive_median",
          "name": "Cognitive: median",
          "value": 0
        },
        {
          "key": "cognitive_p90",
          "name": "Cognitive: p90",
          "value": 3
        },
        {
          "key": "cyclomatic_sum",
          "name": "Cyclomatic: total",
          "value": 2377
        },
        {
          "key": "cyclomatic_max",
          "name": "Cyclomatic: max",
          "value": 41
        },
        {
          "key": "cyclomatic_median",
          "name": "Cyclomatic: median",
          "value": 1
        },
        {
          "key": "cyclomatic_p90",
          "name": "Cyclomatic: p90",
          "value": 3
        }
      ]
    }
  ]
}